honegumi/__init__.py
honegumi/ax/__init__.py
honegumi/ax/_ax.py
honegumi/ax/main.py.jinja
honegumi/ax/utils/__init__.py
honegumi/ax/utils/constants.py
honegumi/core/__init__.py
honegumi/core/_honegumi.py
honegumi/core/honegumi.html.jinja
honegumi/core/honegumi.ipynb.jinja
honegumi/core/utils/constants.py
honegumi-0.4.3.dist-info/licenses/LICENSE.txt
honegumi-0.4.3.dist-info/METADATA
honegumi-0.4.3.dist-info/WHEEL
honegumi-0.4.3.dist-info/top_level.txt
honegumi-0.4.3.dist-info/RECORD
