Metadata-Version: 2.4
Name: honegumi
Version: 0.4.3
Summary: Honegumi (骨組み) is an interactive "skeleton code" generator for API tutorials focusing on optimization packages.
Home-page: https://github.com/sgbaird/honegumi
Author: sgbaird
Author-email: sterling.baird@utoronto.ca
License: MIT
Project-URL: Documentation, https://honegumi.readthedocs.io/
Platform: any
Classifier: Development Status :: 4 - Beta
Classifier: Programming Language :: Python
License-File: LICENSE.txt
Requires-Dist: importlib-metadata; python_version < "3.8"
Requires-Dist: numpy
Requires-Dist: scipy
Requires-Dist: pandas
Requires-Dist: tqdm
Requires-Dist: click
Requires-Dist: Jinja2
Requires-Dist: ax-platform<1
Requires-Dist: black
Requires-Dist: pytest
Requires-Dist: jupytext
Requires-Dist: pydantic
Provides-Extra: dev
Requires-Dist: setuptools; extra == "dev"
Requires-Dist: pytest-cov; extra == "dev"
Requires-Dist: black[jupyter]; extra == "dev"
Requires-Dist: mypy; extra == "dev"
Requires-Dist: pydocstyle; extra == "dev"
Requires-Dist: pre-commit; extra == "dev"
Requires-Dist: pytest-xdist; extra == "dev"
Dynamic: license-file
